oscar_product_tables/__init__.py
oscar_product_tables/apps.py
oscar_product_tables/cell.py
oscar_product_tables/col.py
oscar_product_tables/forms.py
oscar_product_tables/plugins.py
oscar_product_tables/row.py
oscar_product_tables/table.py
oscar_product_tables/dashboard/__init__.py
oscar_product_tables/dashboard/apps.py
oscar_product_tables/dashboard/views.py
oscar_product_tables/static/product_tables/js/product_tables.js
oscar_product_tables/templates/product_tables/field.html
oscar_product_tables/templates/product_tables/form.html
oscar_product_tables/templates/product_tables/table.html
oscar_product_tables/templates/product_tables/table_page.html
oscar_product_tables/templates/product_tables/dashboard/product_table.html
oscar_product_tables/templatetags/__init__.py
oscar_product_tables/templatetags/display_datatype_filters.py
django_oscar_product_tables-0.8.6.dist-info/METADATA
django_oscar_product_tables-0.8.6.dist-info/WHEEL
django_oscar_product_tables-0.8.6.dist-info/top_level.txt
django_oscar_product_tables-0.8.6.dist-info/RECORD
