Metadata-Version: 2.1
Name: django-oscar-product-tables
Version: 0.8.6
Summary: Manage products, their attributevalues and prices on one dynamic table
Author: Snake-Soft
Author-email: info@snake-soft.com
License: BSD
Platform: UNKNOWN
Classifier: Development Status :: 4 - Beta
Classifier: Environment :: Web Environment
Classifier: Framework :: Django
Classifier: Framework :: Django :: 2.2
Classifier: Framework :: Django :: 3.1
Classifier: Framework :: Django :: 3.2
Classifier: Intended Audience :: Developers
Classifier: License :: OSI Approved :: BSD License
Classifier: Operating System :: Unix
Classifier: Programming Language :: Python
Classifier: Programming Language :: Python :: 3
Classifier: Programming Language :: Python :: 3.7
Classifier: Programming Language :: Python :: 3.8
Classifier: Programming Language :: Python :: 3.9
Requires-Dist: django (<3.3,>=2.2)
Requires-Dist: django-oscar (>=3.0)
Requires-Dist: python-dateutil (<3.0,>=2.6)
Provides-Extra: test
Requires-Dist: django-webtest (==1.9.7) ; extra == 'test'
Requires-Dist: pytest-cov (<2.13,>=2.12) ; extra == 'test'
Requires-Dist: pytest-django (<4.5,>=4.4) ; extra == 'test'
Requires-Dist: freezegun (<1.2,>=1.1) ; extra == 'test'
Requires-Dist: sorl-thumbnail ; extra == 'test'
Requires-Dist: factory-boy (<3.3,>=3.2) ; extra == 'test'
Requires-Dist: coverage (<5.6,>=5.5) ; extra == 'test'
Requires-Dist: tox (<3.21,>=3.17) ; extra == 'test'
